wechaty/__init__.py
wechaty/accessory.py
wechaty/accessory_test.py
wechaty/config.py
wechaty/config_test.py
wechaty/exceptions.py
wechaty/plugin.py
wechaty/types.py
wechaty/version.py
wechaty/version_test.py
wechaty/wechaty.py
wechaty/user/__init__.py
wechaty/user/contact.py
wechaty/user/contact_self.py
wechaty/user/favorite.py
wechaty/user/friendship.py
wechaty/user/image.py
wechaty/user/message.py
wechaty/user/mini_program.py
wechaty/user/room.py
wechaty/user/room_invitation.py
wechaty/user/tag.py
wechaty/user/url_link.py
wechaty/utils/__init__.py
wechaty/utils/date_util.py
wechaty/utils/qr_code.py
wechaty/utils/qrcode_terminal.py
wechaty/utils/type_check.py
chaty-0.8.11.dist-info/LICENSE
chaty-0.8.11.dist-info/METADATA
chaty-0.8.11.dist-info/NOTICE
chaty-0.8.11.dist-info/WHEEL
chaty-0.8.11.dist-info/top_level.txt
chaty-0.8.11.dist-info/RECORD
