Metadata-Version: 2.1
Name: chaty
Version: 0.8.11
Summary: Wechaty is a Conversational RPA SDK for Chatbot Makers
Home-page: https://github.com/wechaty/python-wechaty
Author: Jingjing WU (吴京京)
Author-email: wechaty@chatie.io
License: Apache-2.0
Platform: UNKNOWN
Classifier: Programming Language :: Python :: 3.7
Classifier: License :: OSI Approved :: Apache Software License
Classifier: Operating System :: OS Independent
Requires-Dist: pyee
Requires-Dist: requests
Requires-Dist: qrcode
Requires-Dist: lxml
Requires-Dist: wechaty-puppet (>=0.3.dev9)
Requires-Dist: wechaty-puppet-service (>=0.7.dev8)
